coolab/__init__.py
coolab/_utils.py
coolab/confg/__init__.py
coolab/dev/__init__.py
coolab/dev/code/__init__.py
coolab/dev/code/codeapp.py
coolab-1.2.0.dist-info/LICENSE
coolab-1.2.0.dist-info/METADATA
coolab-1.2.0.dist-info/WHEEL
coolab-1.2.0.dist-info/top_level.txt
coolab-1.2.0.dist-info/RECORD
