Metadata-Version: 2.1
Name: coolab
Version: 1.2.0
Summary: Instantly working cool apps you can use on Google Colab!
Home-page: https://github.com/songlinhou/coolab
Author: Ray Hou
Author-email: songlinhou1993@gmail.com
License: MIT
Keywords: colab,vscode,python
Platform: UNKNOWN
Classifier: License :: OSI Approved :: MIT License
Classifier: Programming Language :: Python :: 3
Classifier: Programming Language :: Python :: 3.7
License-File: LICENSE
Requires-Dist: pyngrok
Requires-Dist: pylint
